fastapi_healthcheck/__init__.py
fastapi_healthcheck/checkers/__init__.py
fastapi_healthcheck/checkers/base.py
fastapi_healthcheck/checkers/redis.py
fastapi_healthcheck_flagman-0.0.8.dist-info/LICENSE
fastapi_healthcheck_flagman-0.0.8.dist-info/METADATA
fastapi_healthcheck_flagman-0.0.8.dist-info/WHEEL
fastapi_healthcheck_flagman-0.0.8.dist-info/top_level.txt
fastapi_healthcheck_flagman-0.0.8.dist-info/RECORD
