Metadata-Version: 2.1
Name: fastapi-healthcheck-flagman
Version: 0.0.8
Summary: A small healthcheck package for adding /healthcheck routes to FastAPI projects
Home-page: https://github.com/flagman/fastapi-healthcheck
Author: Pavel Malay
Author-email: flagmansupport@gmail.com
License: UNKNOWN
Platform: UNKNOWN
Classifier: Programming Language :: Python :: 3
Classifier: License :: OSI Approved :: MIT License
Classifier: Operating System :: OS Independent
Requires-Python: >=3.6
Requires-Dist: aioredis
